yncalc/calculator.py
yncalc/setup.py
yunasim2024-0.0.1.dist-info/METADATA
yunasim2024-0.0.1.dist-info/WHEEL
yunasim2024-0.0.1.dist-info/top_level.txt
yunasim2024-0.0.1.dist-info/RECORD
