Metadata-Version: 2.1
Name: yunasim2024
Version: 0.0.1
Summary: nice calculator
Home-page: https://github.com/simrok/calc0001
Download-URL: https://github.com/simrok/calc0001
Author: simrok
Classifier: Programming Language :: Python :: 3
Classifier: Programming Language :: Python :: 3.10
Requires-Dist: pytest
